rockethook/__init__.py
rockethook-1.0.4.dist-info/LICENSE
rockethook-1.0.4.dist-info/METADATA
rockethook-1.0.4.dist-info/WHEEL
rockethook-1.0.4.dist-info/top_level.txt
rockethook-1.0.4.dist-info/RECORD
