Metadata-Version: 2.1
Name: rockethook
Version: 1.0.4
Summary: Simple library for posting to Rocket.Chat via webhooks a.k.a. integrations.
Home-page: https://github.com/gevial/rockethook
Author: Gennady Aleksandrov
Author-email: gevial@yahoo.com
License: MIT
License-File: LICENSE
